ffdb.py
ffdb-2.5.7.data/scripts/extractor.py
ffdb-2.5.7.data/scripts/indexer.py
ffdb-2.5.7.data/scripts/merger.py
ffdb-2.5.7.data/scripts/remover.py
ffdb-2.5.7.dist-info/LICENSE
ffdb-2.5.7.dist-info/METADATA
ffdb-2.5.7.dist-info/WHEEL
ffdb-2.5.7.dist-info/top_level.txt
ffdb-2.5.7.dist-info/RECORD
