Metadata-Version: 2.1
Name: ffdb
Version: 2.5.7
Summary: ffdb
Home-page: https://github.com/g-insana/ffdb.py
Author: Dr Giuseppe Insana
Author-email: insana@insana.net
License: AGPL
Classifier: Programming Language :: Python :: 3
Classifier: License :: OSI Approved :: GNU Affero General Public License v3
Classifier: Operating System :: OS Independent
Requires-Python: >=3.5
License-File: LICENSE
Requires-Dist: tqdm
Requires-Dist: sortedcontainers
Requires-Dist: requests
Requires-Dist: pycryptodomex
